meshkernel/__init__.py
meshkernel/c_structures.py
meshkernel/errors.py
meshkernel/libMeshKernelApi.so
meshkernel/meshkernel.py
meshkernel/py_structures.py
meshkernel/utils.py
meshkernel/version.py
meshkernel.libs/libgomp-24e2ab19.so.1.0.0
meshkernel-8.2.2.dist-info/METADATA
meshkernel-8.2.2.dist-info/WHEEL
meshkernel-8.2.2.dist-info/top_level.txt
meshkernel-8.2.2.dist-info/RECORD
meshkernel-8.2.2.dist-info/licenses/LICENSE
meshkernel-8.2.2.dist-info/sboms/auditwheel.cdx.json
