Metadata-Version: 2.4
Name: meshkernel
Version: 8.2.2
Summary: `meshkernel` is a library which can be used to manipulate meshes.
Home-page: https://github.com/Deltares/MeshKernelPy
Author: Julian Hofer, Prisca van der Sluis, Luca Carniato
Author-email: julian.hofer@deltares.nl, prisca.vandersluis@deltares.nl, luca.carniato@deltares.nl
License: MIT
Platform: Windows
Platform: Linux
Platform: macOS
Classifier: Topic :: Scientific/Engineering :: Mathematics
Requires-Python: >=3.8
License-File: LICENSE
Requires-Dist: numpy>=1.22
Requires-Dist: matplotlib>=3.6
Provides-Extra: tests
Requires-Dist: pytest; extra == "tests"
Requires-Dist: pytest-cov; extra == "tests"
Requires-Dist: nbval; extra == "tests"
Provides-Extra: lint
Requires-Dist: flake8; extra == "lint"
Requires-Dist: black; extra == "lint"
Requires-Dist: isort; extra == "lint"
Provides-Extra: docs
Requires-Dist: sphinx; extra == "docs"
Requires-Dist: sphinx_book_theme; extra == "docs"
Requires-Dist: myst_nb; extra == "docs"
Dynamic: author
Dynamic: author-email
Dynamic: classifier
Dynamic: description
Dynamic: description-content-type
Dynamic: home-page
Dynamic: license
Dynamic: license-file
Dynamic: platform
Dynamic: provides-extra
Dynamic: requires-dist
Dynamic: requires-python
Dynamic: summary
